{
  "id": "inventory",
  "name": "Inventory",
  "description": "Parts, stock, suppliers",
  "status": "stable",
  "version": "1.0.0",
  "category": "Operations",
  "hidden": false,
  "permissions": [
    "module:inventory:view",
    "module:inventory:manage"
  ],
  "routes": [
    {
      "path": "/dashboard/#module-inventory",
      "label": "Inventory"
    }
  ],
  "navigation": {
    "sidebar": true,
    "mobile": true
  },
  "api": {
    "dispatcher": "/api/module/:module/:action"
  },
  "widgets": [
    "inventory-summary"
  ]
}