{
  "id": "maintenance-plans",
  "version": "1.0.0",
  "name": "Maintenance Plans",
  "description": "Drop-in module for Maintenance Plans.",
  "category": "AI",
  "minimumPlatform": "1.0.0",
  "status": "stable",
  "enabledByDefault": true,
  "hidden": false,
  "beta": false,
  "experimental": false,
  "workspaces": [
    "owner",
    "admin",
    "manager",
    "worker",
    "client"
  ],
  "nav": {
    "label": "Maintenance",
    "icon": "◼",
    "order": 16
  },
  "permissions": [
    {
      "key": "maintenance.view",
      "label": "Use Maintenance Plans",
      "group": "Maintenance Plans",
      "defaultRoles": [
        "owner",
        "admin",
        "manager"
      ]
    }
  ],
  "dependencies": [],
  "frontend": {
    "entry": "/modules/maintenance-plans/frontend/module.js",
    "style": "/modules/maintenance-plans/frontend/module.css"
  },
  "api": {
    "handler": "modules/maintenance-plans/backend/api.mjs",
    "routes": [
      {
        "method": [
          "GET",
          "POST"
        ],
        "path": "/records",
        "permission": "maintenance.view"
      }
    ]
  },
  "homepageSections": [],
  "workflows": []
}