{
  "id": "public-quote-viewer",
  "title": "Public Quote Viewer",
  "description": "Secure public quote acceptance pages",
  "version": "1.0.0",
  "icon": "📄",
  "workspace": "public",
  "category": "public",
  "enabledByDefault": true,
  "dependencies": [],
  "permissions": [
    "public-quote-viewer:read",
    "public-quote-viewer:write"
  ],
  "routes": [
    {
      "path": "/dashboard/public-quote-viewer",
      "title": "Public Quote Viewer",
      "view": "public-quote-viewer-view",
      "workspace": "public"
    }
  ],
  "nav": {
    "label": "Public Quote Viewer",
    "path": "/dashboard/public-quote-viewer",
    "icon": "📄",
    "workspace": "public",
    "order": 22
  },
  "mobileNav": {
    "label": "Public Quote Viewer",
    "path": "/dashboard/public-quote-viewer",
    "icon": "📄"
  },
  "api": [
    {
      "method": "GET",
      "path": "public-quote-viewer/summary",
      "handler": "summary.mjs"
    }
  ],
  "events": [
    "workflow.updated",
    "module.toggled"
  ],
  "settings": {
    "configurable": true
  },
  "homepageSections": [],
  "installerSteps": [],
  "migrations": [
    "netlify/migrations/0001_initial_platform.sql"
  ]
}